backups/__init__.py
backups/cli.py
backups/compress.py
backups/context.py
backups/data.py
backups/logger.py
backups/mysql.py
backups/notify.py
backups/postgres.py
backups/runner.py
backups/system.py
backups/upload.py
backups/version.py
backups-0.3.7.dist-info/LICENSE
backups-0.3.7.dist-info/METADATA
backups-0.3.7.dist-info/WHEEL
backups-0.3.7.dist-info/entry_points.txt
backups-0.3.7.dist-info/top_level.txt
backups-0.3.7.dist-info/RECORD
