Metadata-Version: 2.1
Name: backups
Version: 0.3.7
Summary: Database backup utility
Home-page: https://github.com/ptdorf/backups
Author: ptdorf
Author-email: ptdorf@gmail.com
License: MIT
Download-URL: https://github.com/ptdorf/backups/tarball/master
Keywords: backups backup mysql
Platform: UNKNOWN
Classifier: Development Status :: 3 - Alpha
Classifier: Intended Audience :: Developers
Classifier: Topic :: Software Development :: Build Tools
Classifier: License :: OSI Approved :: MIT License
Classifier: Programming Language :: Python :: 3
Requires-Python: >=3
Requires-Dist: docopt
Requires-Dist: pyyaml (>=5.3.1)
Requires-Dist: mysqlclient
Requires-Dist: requests
